<?xml version = '1.0' encoding = 'UTF-8'?>
<Relation class="oracle.dbtools.crest.model.design.logical.Relation" name="Relation_5" directorySegmentName="seg_0" id="194CB179-113B-1159-5746-55FAB73897C8">
<createdBy>computer</createdBy>
<createdTime>2021-12-27 19:30:31 UTC</createdTime>
<ownerDesignName>DataModeler</ownerDesignName>
<engineerTo>
<item key="FE4A1F17-A0E5-3F0A-5F09-F9F605137488" value="true"/>
</engineerTo>
<sourcePk>AE9F39B1-2A22-3F74-8E7F-9AA08EE5ABD4</sourcePk>
<identifying>true</identifying>
<optionalSource>true</optionalSource>
<optionalTarget>false</optionalTarget>
<sourceCardinality>1</sourceCardinality>
<sourceEntity>9D014169-118B-783E-86D1-BA6F9B374CF6</sourceEntity>
<targetCardinalityString>*</targetCardinalityString>
<targetEntity>9D11ADA7-2E55-5C0E-05C5-926A0778E9F0</targetEntity>
<transferable>true</transferable>
<deleteRule>NO ACTION</deleteRule>
</Relation>